requests_proxy_rotation/__init__.py
requests_proxy_rotation/requests_proxy_rotation.py
requests_proxy_rotation-1.0.1.dist-info/LICENSE
requests_proxy_rotation-1.0.1.dist-info/METADATA
requests_proxy_rotation-1.0.1.dist-info/WHEEL
requests_proxy_rotation-1.0.1.dist-info/top_level.txt
requests_proxy_rotation-1.0.1.dist-info/RECORD
