Metadata-Version: 2.1
Name: requests-proxy-rotation
Version: 1.0.1
Summary: A wrapped version of requests. Help bypassing limitation of API by automatic rotating proxy
Home-page: UNKNOWN
Author: phannt
Author-email: phan123123@gmail.com
License: Apache License 2.0
Keywords: python library requests proxy rotation
Platform: UNKNOWN
Classifier: Programming Language :: Python :: 3
Classifier: License :: OSI Approved :: Apache Software License
Classifier: Operating System :: OS Independent
Requires-Python: >=3.6
Requires-Dist: requests
